README.md
setup.py
bgnd_dist/Binomialdistribution.py
bgnd_dist/Gaussiandistribution.py
bgnd_dist/Generaldistribution.py
bgnd_dist/__init__.py
bgnd_dist.egg-info/PKG-INFO
bgnd_dist.egg-info/SOURCES.txt
bgnd_dist.egg-info/dependency_links.txt
bgnd_dist.egg-info/not-zip-safe
bgnd_dist.egg-info/top_level.txt