Metadata-Version: 2.1
Name: bgnd-dist
Version: 1.2
Summary: Binomial and Gaussian distributions
Home-page: UNKNOWN
Author: Betini Akarandut
Author-email: betiniakarandut@gmail.com
License: UNKNOWN
Platform: UNKNOWN
